savecode/__init__.py
savecode/__main__.py
savecode/cli.py
savecode/constants/__init__.py
savecode/constants/reserved_keys.py
savecode/plugin_manager/__init__.py
savecode/plugin_manager/decorators.py
savecode/plugin_manager/manager.py
savecode/plugins/__init__.py
savecode/plugins/extra_args.py
savecode/plugins/gather.py
savecode/plugins/git_status.py
savecode/plugins/save.py
savecode/utils/__init__.py
savecode/utils/cli_args.py
savecode/utils/clipboard.py
savecode/utils/colors.py
savecode/utils/display.py
savecode/utils/error_handler.py
savecode/utils/logger.py
savecode/utils/path_utils.py
savecode-2.1.5.dist-info/METADATA
savecode-2.1.5.dist-info/WHEEL
savecode-2.1.5.dist-info/entry_points.txt
savecode-2.1.5.dist-info/top_level.txt
savecode-2.1.5.dist-info/RECORD
