Metadata-Version: 2.4
Name: savecode
Version: 2.1.5
Summary: A utility to save source code from directories and files into a single output file with smart file filtering, streaming, and progress tracking.
Author-email: Austin Wagner <austinwagner@msn.com>
License: MIT
Project-URL: Homepage, https://github.com/wagner-austin/savecode
Project-URL: Bug Tracker, https://github.com/wagner-austin/savecode/issues
Keywords: code,backup,source code,extraction,utility
Classifier: Development Status :: 5 - Production/Stable
Classifier: Environment :: Console
Classifier: Intended Audience :: Developers
Classifier: License :: OSI Approved :: MIT License
Classifier: Programming Language :: Python :: 3
Classifier: Programming Language :: Python :: 3.11
Classifier: Topic :: Software Development :: Libraries :: Python Modules
Classifier: Topic :: Utilities
Requires-Python: >=3.11
Requires-Dist: tqdm>=4.65.0
Requires-Dist: pyperclip>=1.8
Provides-Extra: dev
Requires-Dist: pytest>=8.0; extra == "dev"
Requires-Dist: pytest-asyncio; extra == "dev"
Requires-Dist: pytest-env; extra == "dev"
Requires-Dist: ruff>=0.4; extra == "dev"
Requires-Dist: black>=24.3; extra == "dev"
Requires-Dist: mypy>=1.10; extra == "dev"
Requires-Dist: build; extra == "dev"
Requires-Dist: twine; extra == "dev"
